{
  "machine_details": {
    "filename_key": "g4dn.xlarge",
    "type": "aws"
  },
  "test_runs": [
    {
      "end_time": "2022-10-07 21:59:33.471867",
      "start_time": "2022-10-07 21:45:42.180683",
      "time_delta": "0:13:51.291184"
    },
    {
      "end_time": "2022-10-07 22:13:22.138858",
      "start_time": "2022-10-07 21:59:33.472315",
      "time_delta": "0:13:48.666543"
    },
    {
      "end_time": "2022-10-07 22:27:11.271152",
      "start_time": "2022-10-07 22:13:22.139334",
      "time_delta": "0:13:49.131818"
    }
  ]
}